docs/source/conf.py
docs/source/index.rst
docs/source/ptcc_library.Examples.rst
docs/source/ptcc_library.Installation.rst
docs/source/ptcc_library.Overview.rst
docs/source/ptcc_library.communication.rst
docs/source/ptcc_library.rst
docs/source/ptcc_library.utils-defines-baseobj.rst
docs/source/_static/PTCC-01-TEC-controllers-2048x1051.jpg
docs/source/_static/custom.css
examples/example.py
examples/monitor_basic_params.py
examples/monitor_lab_m_params.py
examples/monitor_monitor_params.py
examples/monitor_status.py
examples/read_device_iden.py
examples/read_full_response.py
examples/read_module_iden.py
examples/read_tec_current.py
examples/set_lab_m_gain.py
examples/set_temperature.py
ptcc_library/__init__.py
ptcc_library/_version.py
ptcc_library/ptcc_defines.py
ptcc_library/ptcc_object.py
ptcc_library/ptcc_utils.py
ptcc_library/communication/__init__.py
ptcc_library/communication/ptcc_communication_iface.py
ptcc_library/communication/ptcc_device.py
ptcc_library/communication/ptcc_protocol.py
ptcc_library-0.2.0.dist-info/licenses/LICENSE
ptcc_library-0.2.0.dist-info/METADATA
ptcc_library-0.2.0.dist-info/WHEEL
ptcc_library-0.2.0.dist-info/top_level.txt
ptcc_library-0.2.0.dist-info/RECORD
