Metadata-Version: 2.4
Name: ptcc-library
Version: 0.2.0
Summary: This is a modular Python library for communicating with PTCC hardware devices over a custom byte-based protocol. It supports message construction, parsing, throttled I/O communication, device detection, and callback-based event handling.
Author-email: Wojceich Szczytko <wszczytko@vigo.com.pl>
License-Expression: MIT
Keywords: PTCC
Requires-Python: >=3.12
License-File: LICENSE
Dynamic: license-file
